mkdocs_toc_plugin/__init__.py
mkdocs_toc_plugin/plugin.py
mkdocs_toc_plugin/utils.py
mkdocs_toc_plugin/css/toc_extra.css
mkdocs_toc_plugin/templates/toc.html
mkdocs_toc_plugin-0.0.2.dist-info/METADATA
mkdocs_toc_plugin-0.0.2.dist-info/WHEEL
mkdocs_toc_plugin-0.0.2.dist-info/entry_points.txt
mkdocs_toc_plugin-0.0.2.dist-info/top_level.txt
mkdocs_toc_plugin-0.0.2.dist-info/RECORD
