Metadata-Version: 2.1
Name: mkdocs-toc-plugin
Version: 0.0.2
Summary: A MkDocs plugin that create custom toc
Author: TonyCrane
Author-email: me@tonycrane.cc
License: MIT
Keywords: mkdocs python markdown
Classifier: Development Status :: 3 - Alpha
Classifier: Intended Audience :: Developers
Classifier: Intended Audience :: Information Technology
Classifier: License :: OSI Approved :: MIT License
Classifier: Programming Language :: Python
Classifier: Programming Language :: Python :: 3.5
Classifier: Programming Language :: Python :: 3.6
Classifier: Programming Language :: Python :: 3.7
Classifier: Programming Language :: Python :: 3.8
Classifier: Programming Language :: Python :: 3.9
Classifier: Programming Language :: Python :: 3.10
Requires-Python: >=3.5
Requires-Dist: mkdocs
Requires-Dist: pyyaml
